mvts_analyzer/__init__.py
mvts_analyzer/main.py
mvts_analyzer/example/example_data.csv
mvts_analyzer/example/example_data.xlsx
mvts_analyzer/graphing/__init__.py
mvts_analyzer/graphing/graph_data.py
mvts_analyzer/graphing/graph_settings_controller.py
mvts_analyzer/graphing/graph_settings_model.py
mvts_analyzer/graphing/graph_settings_view.py
mvts_analyzer/graphing/plotter/__init__.py
mvts_analyzer/graphing/plotter/collection_selector.py
mvts_analyzer/graphing/plotter/plot_wrapper.py
mvts_analyzer/res/__init__.py
mvts_analyzer/res/app_resources_rc.py
mvts_analyzer/ui/__init__.py
mvts_analyzer/ui/apply_python_window_ui.py
mvts_analyzer/ui/main_window_ui.py
mvts_analyzer/ui/merge_column_window_ui.py
mvts_analyzer/ui/rename_label_window_ui.py
mvts_analyzer/utility/__init__.py
mvts_analyzer/utility/data_analysis.py
mvts_analyzer/utility/df_utility.py
mvts_analyzer/utility/general_utility.py
mvts_analyzer/utility/gui_utility.py
mvts_analyzer/widgets/__init__.py
mvts_analyzer/widgets/collapsible_groupbox.py
mvts_analyzer/widgets/combobox_list.py
mvts_analyzer/widgets/datastructures.py
mvts_analyzer/widgets/datetime_range.py
mvts_analyzer/widgets/range_slider.py
mvts_analyzer/widgets/range_slider_with_box.py
mvts_analyzer/widgets/range_sliders_with_boxes.py
mvts_analyzer/widgets/variable_range.py
mvts_analyzer/widgets/widget_list.py
mvts_analyzer/windows/__init__.py
mvts_analyzer/windows/apply_python_window.py
mvts_analyzer/windows/labeler_window.py
mvts_analyzer/windows/load_type_selection_window.py
mvts_analyzer/windows/main_window.py
mvts_analyzer/windows/merge_column_window.py
mvts_analyzer/windows/rename_label_window.py
mvts_analyzer/windows/tabbed_matplotlib_window.py
MVTS_Analyzer-0.0.2.dist-info/LICENSE
MVTS_Analyzer-0.0.2.dist-info/METADATA
MVTS_Analyzer-0.0.2.dist-info/WHEEL
MVTS_Analyzer-0.0.2.dist-info/entry_points.txt
MVTS_Analyzer-0.0.2.dist-info/top_level.txt
MVTS_Analyzer-0.0.2.dist-info/RECORD
