Metadata-Version: 2.1
Name: MVTS-Analyzer
Version: 0.0.2
Summary: Plotting, annotation and analysis tools for multivariate time series data
Home-page: https://github.com/Woutah/MVTS-Analyzer
Author: Wouter Stokman
License: LGPLv2
License-File: LICENSE
Requires-Dist: keyboard >=0.10.4
Requires-Dist: matplotlib >=3.6.0
Requires-Dist: numpy >=1.15.0
Requires-Dist: pandas >=1.2.0
Requires-Dist: PySide6 >=6.2.0
